stacker/__init__.py
stacker/file_manipulation.py
stacker/kmeans.py
stacker/pairwise_distance.py
stacker/residue_movement.py
stacker/vector.py
stacker/visualization.py
pistacker-1.1.5.dist-info/LICENSE
pistacker-1.1.5.dist-info/METADATA
pistacker-1.1.5.dist-info/WHEEL
pistacker-1.1.5.dist-info/entry_points.txt
pistacker-1.1.5.dist-info/top_level.txt
pistacker-1.1.5.dist-info/RECORD
