Metadata-Version: 2.1
Name: pistacker
Version: 1.1.5
Summary: Analyzes Pi-Stacking in Molecular Dynamics Trajectories
Home-page: https://github.com/esakkas24/stacker
Author: Eric D. Sakkas
Author-email: esakkas@wesleyan.edu
Requires-Python: >=3.10
License-File: LICENSE
Requires-Dist: scikit-learn
Requires-Dist: mdtraj
Requires-Dist: pandas
Requires-Dist: numpy
Requires-Dist: matplotlib
Requires-Dist: seaborn
Requires-Dist: sphinx
Requires-Dist: sphinx_design
Requires-Dist: sphinx_book_theme
Requires-Dist: numpydoc
Requires-Dist: latex
